LICENSE
README.md
setup.py
pyqt_components/__init__.py
pyqt_components/__main__.py
pyqt_components.egg-info/PKG-INFO
pyqt_components.egg-info/SOURCES.txt
pyqt_components.egg-info/dependency_links.txt
pyqt_components.egg-info/top_level.txt
pyqt_components/commands/__init__.py
pyqt_components/commands/commands.py
pyqt_components/commands/init.py
pyqt_components/packages/__init__.py
pyqt_components/packages/app/__init__.py
pyqt_components/packages/app/app.py
pyqt_components/packages/app/components/__init__.py
pyqt_components/packages/app/components/loader.py
pyqt_components/packages/app/signals/__init__.py
pyqt_components/packages/app/signals/controller.py