Metadata-Version: 2.1
Name: pyqt-components
Version: 0.1
Summary: Package for PyQt component architecture
Home-page: 
Author: draksplay
Author-email: draksplay@mail.ru
License: MIT
License-File: LICENSE
